polygone/__main__.py
polygone/cli.py
polygone/log.py
polygone/packer.py
polygone-0.1.2.dist-info/METADATA
polygone-0.1.2.dist-info/WHEEL
polygone-0.1.2.dist-info/entry_points.txt
polygone-0.1.2.dist-info/RECORD
